CHANGELOG.md
LICENSE
MANIFEST.in
README.md
pyproject.toml
setup.cfg
setup.py
diagrams/__init__.py
diagrams/pyproject.toml
diagrams/alibabacloud/__init__.py
diagrams/alibabacloud/analytics.py
diagrams/alibabacloud/application.py
diagrams/alibabacloud/communication.py
diagrams/alibabacloud/compute.py
diagrams/alibabacloud/database.py
diagrams/alibabacloud/iot.py
diagrams/alibabacloud/network.py
diagrams/alibabacloud/security.py
diagrams/alibabacloud/storage.py
diagrams/alibabacloud/web.py
diagrams/aws/__init__.py
diagrams/aws/analytics.py
diagrams/aws/ar.py
diagrams/aws/blockchain.py
diagrams/aws/business.py
diagrams/aws/compute.py
diagrams/aws/cost.py
diagrams/aws/database.py
diagrams/aws/devtools.py
diagrams/aws/enablement.py
diagrams/aws/enduser.py
diagrams/aws/engagement.py
diagrams/aws/game.py
diagrams/aws/general.py
diagrams/aws/integration.py
diagrams/aws/iot.py
diagrams/aws/management.py
diagrams/aws/media.py
diagrams/aws/migration.py
diagrams/aws/ml.py
diagrams/aws/mobile.py
diagrams/aws/network.py
diagrams/aws/quantum.py
diagrams/aws/robotics.py
diagrams/aws/satellite.py
diagrams/aws/security.py
diagrams/aws/storage.py
diagrams/azure/__init__.py
diagrams/azure/aiml.py
diagrams/azure/analytics.py
diagrams/azure/appservices.py
diagrams/azure/azureecosystem.py
diagrams/azure/azurestack.py
diagrams/azure/blockchain.py
diagrams/azure/compute.py
diagrams/azure/containers.py
diagrams/azure/database.py
diagrams/azure/databases.py
diagrams/azure/devops.py
diagrams/azure/general.py
diagrams/azure/hybridmulticloud.py
diagrams/azure/identity.py
diagrams/azure/integration.py
diagrams/azure/intune.py
diagrams/azure/iot.py
diagrams/azure/managementgovernance.py
diagrams/azure/menu.py
diagrams/azure/migrate.py
diagrams/azure/migration.py
diagrams/azure/mixedreality.py
diagrams/azure/ml.py
diagrams/azure/mobile.py
diagrams/azure/monitor.py
diagrams/azure/network.py
diagrams/azure/networking.py
diagrams/azure/newicons.py
diagrams/azure/other.py
diagrams/azure/security.py
rsaz_diagrams.egg-info/PKG-INFO
rsaz_diagrams.egg-info/SOURCES.txt
rsaz_diagrams.egg-info/dependency_links.txt
rsaz_diagrams.egg-info/entry_points.txt
rsaz_diagrams.egg-info/requires.txt
rsaz_diagrams.egg-info/top_level.txt
