Metadata-Version: 2.4
Name: rsaz-diagrams
Version: 0.24.6
Summary: Azure Extended version of diagrams
Home-page: https://github.com/rajesh-ms/diagrams
Author: Diagrams-web
Author-email: no_spam@nowhere.mail
Maintainer: rajesh-ms
Maintainer-email: rajesh-ms@nowhere.mail
Requires-Python: >=3.8,<4.0
License-File: LICENSE
Requires-Dist: graphviz<0.21.0,>=0.13.2
Requires-Dist: jinja2<4.0,>=2.10
Dynamic: author
Dynamic: author-email
Dynamic: description
Dynamic: home-page
Dynamic: license-file
Dynamic: maintainer
Dynamic: maintainer-email
Dynamic: requires-dist
Dynamic: requires-python
Dynamic: summary
